[
	{
		"inputs": [
			{
				"internalType": "uint256",
				"name": "_projectid",
				"type": "uint256"
			},
			{
				"internalType": "string",
				"name": "_checksum",
				"type": "string"
			}
		],
		"name": "addFile",
		"outputs": [
			{
				"internalType": "uint256",
				"name": "",
				"type": "uint256"
			}
		],
		"stateMutability": "nonpayable",
		"type": "function"
	},
	{
		"inputs": [],
		"name": "addProject",
		"outputs": [
			{
				"components": [
					{
						"internalType": "address",
						"name": "author",
						"type": "address"
					},
					{
						"components": [
							{
								"internalType": "string",
								"name": "hash",
								"type": "string"
							},
							{
								"internalType": "address",
								"name": "author",
								"type": "address"
							}
						],
						"internalType": "struct AMProject.File[]",
						"name": "files",
						"type": "tuple[]"
					}
				],
				"internalType": "struct AMProject.Project",
				"name": "",
				"type": "tuple"
			}
		],
		"stateMutability": "nonpayable",
		"type": "function"
	},
	{
		"inputs": [
			{
				"internalType": "uint256",
				"name": "_projectid",
				"type": "uint256"
			},
			{
				"internalType": "uint256",
				"name": "_fileid",
				"type": "uint256"
			}
		],
		"name": "getFile",
		"outputs": [
			{
				"components": [
					{
						"internalType": "string",
						"name": "hash",
						"type": "string"
					},
					{
						"internalType": "address",
						"name": "author",
						"type": "address"
					}
				],
				"internalType": "struct AMProject.File",
				"name": "",
				"type": "tuple"
			}
		],
		"stateMutability": "view",
		"type": "function"
	},
	{
		"inputs": [
			{
				"internalType": "uint256",
				"name": "_projectid",
				"type": "uint256"
			}
		],
		"name": "getProject",
		"outputs": [
			{
				"components": [
					{
						"internalType": "address",
						"name": "author",
						"type": "address"
					},
					{
						"components": [
							{
								"internalType": "string",
								"name": "hash",
								"type": "string"
							},
							{
								"internalType": "address",
								"name": "author",
								"type": "address"
							}
						],
						"internalType": "struct AMProject.File[]",
						"name": "files",
						"type": "tuple[]"
					}
				],
				"internalType": "struct AMProject.Project",
				"name": "",
				"type": "tuple"
			}
		],
		"stateMutability": "view",
		"type": "function"
	},
	{
		"inputs": [],
		"name": "getProjectCount",
		"outputs": [
			{
				"internalType": "uint256",
				"name": "",
				"type": "uint256"
			}
		],
		"stateMutability": "view",
		"type": "function"
	},
	{
		"inputs": [],
		"name": "listProjects",
		"outputs": [
			{
				"components": [
					{
						"internalType": "address",
						"name": "author",
						"type": "address"
					},
					{
						"components": [
							{
								"internalType": "string",
								"name": "hash",
								"type": "string"
							},
							{
								"internalType": "address",
								"name": "author",
								"type": "address"
							}
						],
						"internalType": "struct AMProject.File[]",
						"name": "files",
						"type": "tuple[]"
					}
				],
				"internalType": "struct AMProject.Project[]",
				"name": "",
				"type": "tuple[]"
			}
		],
		"stateMutability": "view",
		"type": "function"
	},
	{
		"inputs": [],
		"name": "projectCount",
		"outputs": [
			{
				"internalType": "uint256",
				"name": "",
				"type": "uint256"
			}
		],
		"stateMutability": "view",
		"type": "function"
	},
	{
		"inputs": [
			{
				"internalType": "uint256",
				"name": "",
				"type": "uint256"
			}
		],
		"name": "projectList",
		"outputs": [
			{
				"internalType": "address",
				"name": "author",
				"type": "address"
			}
		],
		"stateMutability": "view",
		"type": "function"
	}
]